timesTable/__init__.py
timesTable/__main__.py
timesTable-2.0.0.dist-info/LICENSE
timesTable-2.0.0.dist-info/METADATA
timesTable-2.0.0.dist-info/WHEEL
timesTable-2.0.0.dist-info/entry_points.txt
timesTable-2.0.0.dist-info/top_level.txt
timesTable-2.0.0.dist-info/RECORD
