Metadata-Version: 2.2
Name: timesTable
Version: 2.0.0
Summary: prints an N x N multiplication table
Home-page: https://github.com/jrowellfx/timesTable
Author: James Philip Rowell
Author-email: james@alpha-eleven.com
Classifier: Programming Language :: Python :: 3
Classifier: License :: OSI Approved :: BSD License
Classifier: Operating System :: POSIX
Classifier: Operating System :: Unix
Classifier: Operating System :: MacOS
Classifier: Development Status :: 5 - Production/Stable
Requires-Python: >=3.6, <4
License-File: LICENSE
Requires-Dist: python-baseconv>=1.2.2
Dynamic: author
Dynamic: author-email
Dynamic: classifier
Dynamic: description
Dynamic: description-content-type
Dynamic: home-page
Dynamic: requires-dist
Dynamic: requires-python
Dynamic: summary
